{
    "cells" : [
        {
            "cell_name": "Cell ke-1",
            "qualifications": [
                {
                    "name" : "Uppper Bracket Ronde 1",
                    "winners": [
                        {
                            "matches" : [
                                {
                                    "winn" : 0,
                                    "teams" :[
                                        {
                                            "id" : "1",
                                            "team_name" : "TEAM B",
                                            "logo" : "https://am-a.akamaihd.net/image?resize=72:&f=http%3A%2F%2Fstatic.lolesports.com%2Fteams%2F1632335599999_Cloud9C9-03-FullonLight.png",
                                            "score" : 1
                                        },
                                        {
                                            "id" : "2",
                                            "team_name" : "TEAM C",
                                            "logo" : "https://am-a.akamaihd.net/image?resize=36:&f=http%3A%2F%2Fstatic.lolesports.com%2Fteams%2F1667815424271_600px-KRU_Esports_allmode.png",
                                            "score" : 0
                                        }
                                    ]
                                },{
                                    "winn" : 0,
                                    "teams" :[
                                        {
                                            "id" : "3",
                                            "team_name" : "TEAM D",
                                            "logo" : "https://am-a.akamaihd.net/image?resize=36:&f=http%3A%2F%2Fstatic.lolesports.com%2Fteams%2F1635528110402_G2Link.png",
                                            "score" : 1
                                        },
                                        {
                                            "id" : "4",
                                            "team_name" : "TEAM E",
                                            "logo" : "",
                                            "score" : 0
                                        }
                                    ]
                                }
                            ]
                        },{
                            "matches" : [
                                {
                                    "winn" : 1,
                                    "teams" :[
                                        {
                                            "id" : "5",
                                            "team_name" : "TEAM F",
                                            "logo" : "https://am-a.akamaihd.net/image?resize=36:&f=http%3A%2F%2Fstatic.lolesports.com%2Fteams%2F1668071480942_Team_Liquid_Logo_Horizontal.png",
                                            "score" : 0
                                        },
                                        {
                                            "id" : "6",
                                            "team_name" : "TEAM G",
                                            "logo" : "https://am-a.akamaihd.net/image?resize=36:&f=http%3A%2F%2Fstatic.lolesports.com%2Fteams%2F1633015576759_Guild_Esports_allmode.png",
                                            "score" : 1
                                        }
                                    ]
                                },{
                                    "winn" : 1,
                                    "teams" :[
                                        {
                                            "id" : "7",
                                            "team_name" : "TEAM H",
                                            "logo" : "https://am-a.akamaihd.net/image?resize=36:&f=http%3A%2F%2Fstatic.lolesports.com%2Fteams%2F1667815441757_62bd90e55f45a.png",
                                            "score" : 0
                                        },
                                        {
                                            "id" : "8",
                                            "team_name" : "TEAM I",
                                            "logo" : "https://am-a.akamaihd.net/image?resize=36:&f=http%3A%2F%2Fstatic.lolesports.com%2Fteams%2F1667815449519_rebellion-logo-mark-green1.png",
                                            "score" : 1
                                        }
                                    ]
                                }
                            ]
                        }
                    ]
                },
                {
                    "name" : "Uppper Bracket Ronde 2",
                    "winners": [
                        {
                            "matches" : [
                                {
                                    "winn" : 0,
                                    "teams" :[
                                        {
                                            "id" : "1",
                                            "team_name" : "TEAM B",
                                            "logo" : "https://am-a.akamaihd.net/image?resize=72:&f=http%3A%2F%2Fstatic.lolesports.com%2Fteams%2F1632335599999_Cloud9C9-03-FullonLight.png",
                                            "score" : 1
                                        },
                                        {
                                            "id" : "3",
                                            "team_name" : "TEAM D",
                                            "logo" : "https://am-a.akamaihd.net/image?resize=36:&f=http%3A%2F%2Fstatic.lolesports.com%2Fteams%2F1635528110402_G2Link.png",
                                            "score" : 0
                                        }
                                    ]
                                },{
                                    "winn" : 0,
                                    "teams" :[
                                        {
                                            "id" : "8",
                                            "team_name" : "TEAM I",
                                            "logo" : "https://am-a.akamaihd.net/image?resize=36:&f=http%3A%2F%2Fstatic.lolesports.com%2Fteams%2F1667815449519_rebellion-logo-mark-green1.png",
                                            "score" : 1
                                        },
                                        {
                                            "id" : "6",
                                            "team_name" : "TEAM G",
                                            "logo" : "https://am-a.akamaihd.net/image?resize=36:&f=http%3A%2F%2Fstatic.lolesports.com%2Fteams%2F1633015576759_Guild_Esports_allmode.png",
                                            "score" : 0
                                        }
                                    ]
                                }
                            ]
                        }
                    ]
                },
                {
                    "name" : "Upper Bracket - Final",
                    "winners": [
                        {
                            "matches" : [
                                {
                                    "winn" : 1,
                                    "teams" :[
                                        {
                                            "id" : "1",
                                            "team_name" : "TEAM B",
                                            "logo" : "https://am-a.akamaihd.net/image?resize=72:&f=http%3A%2F%2Fstatic.lolesports.com%2Fteams%2F1632335599999_Cloud9C9-03-FullonLight.png",
                                            "score" : 1
                                        },
                                        {
                                            "id" : "8",
                                            "team_name" : "TEAM I",
                                            "logo" : "https://am-a.akamaihd.net/image?resize=36:&f=http%3A%2F%2Fstatic.lolesports.com%2Fteams%2F1667815449519_rebellion-logo-mark-green1.png",
                                            "score" : 2
                                        }
                                    ]
                                }
                            ]
                        }
                    ]
                },
                {
                    "name" : "Final",
                    "winners": [
                        {
                            "matches" : [
                                {
                                    "winn" : null,
                                    "teams" :[
                                        {
                                            "id" : "8",
                                            "team_name" : "TEAM I",
                                            "logo" : "https://am-a.akamaihd.net/image?resize=36:&f=http%3A%2F%2Fstatic.lolesports.com%2Fteams%2F1667815449519_rebellion-logo-mark-green1.png",
                                            "score" : 0
                                        }
                                    ]
                                }
                            ]
                        }
                    ]
                }
            ]
        },
        {
            "cell_name": "Cell ke-2",
            "qualifications": [
                {
                    "name" : "",
                    "winners": []
                },
                {
                    "name" : "Lower Bracket",
                    "winners": [
                        {
                            "matches" : [
                                {
                                    "winn" : 0,
                                    "teams" :[
                                        {
                                            "id" : "2",
                                            "team_name" : "TEAM C",
                                            "logo" : "https://am-a.akamaihd.net/image?resize=36:&f=http%3A%2F%2Fstatic.lolesports.com%2Fteams%2F1667815424271_600px-KRU_Esports_allmode.png",
                                            "score" : 2
                                        },
                                        {
                                            "id" : "4",
                                            "team_name" : "TEAM E",
                                            "logo" : "",
                                            "score" : 0
                                        }
                                    ]
                                },{
                                    "winn" : 0,
                                    "teams" :[
                                        {
                                            "id" : "5",
                                            "team_name" : "TEAM F",
                                            "logo" : "https://am-a.akamaihd.net/image?resize=36:&f=http%3A%2F%2Fstatic.lolesports.com%2Fteams%2F1668071480942_Team_Liquid_Logo_Horizontal.png",
                                            "score" : 1
                                        },
                                        {
                                            "id" : "7",
                                            "team_name" : "TEAM H",
                                            "logo" : "https://am-a.akamaihd.net/image?resize=36:&f=http%3A%2F%2Fstatic.lolesports.com%2Fteams%2F1667815441757_62bd90e55f45a.png",
                                            "score" : 0
                                        }
                                    ]
                                }
                            ]
                        }
                    ]
                },
                {
                    "name" : "Lower Bracket Ronde 2",
                    "winners": [
                        {
                            "matches" : [
                                {
                                    "winn" : 0,
                                    "teams" :[
                                        {
                                            "id" : "2",
                                            "team_name" : "TEAM C",
                                            "logo" : "https://am-a.akamaihd.net/image?resize=36:&f=http%3A%2F%2Fstatic.lolesports.com%2Fteams%2F1667815424271_600px-KRU_Esports_allmode.png",
                                            "score" : 2
                                        },
                                        {
                                            "id" : "5",
                                            "team_name" : "TEAM F",
                                            "logo" : "https://am-a.akamaihd.net/image?resize=36:&f=http%3A%2F%2Fstatic.lolesports.com%2Fteams%2F1668071480942_Team_Liquid_Logo_Horizontal.png",
                                            "score" : 1
                                        }
                                    ]
                                },{
                                    "winn" : 0,
                                    "teams" :[
                                        {
                                            "id" : "5",
                                            "team_name" : "TEAM F",
                                            "logo" : "https://am-a.akamaihd.net/image?resize=36:&f=http%3A%2F%2Fstatic.lolesports.com%2Fteams%2F1668071480942_Team_Liquid_Logo_Horizontal.png",
                                            "score" : 1
                                        },
                                        {
                                            "id" : "7",
                                            "team_name" : "TEAM H",
                                            "logo" : "https://am-a.akamaihd.net/image?resize=36:&f=http%3A%2F%2Fstatic.lolesports.com%2Fteams%2F1667815441757_62bd90e55f45a.png",
                                            "score" : 0
                                        }
                                    ]
                                }
                            ]
                        }
                    ]
                },
                {
                    "name" : "Lower Bracket Final",
                    "winners": [
                        {
                            "matches" : [
                                {
                                    "winn" : null,
                                    "teams" :[
                                        {
                                            "team_name" : "TEAM S",
                                            "logo" : "https://am-a.akamaihd.net/image?resize=72:&f=http%3A%2F%2Fstatic.lolesports.com%2Fteams%2F1632335599999_Cloud9C9-03-FullonLight.png",
                                            "score" : 0
                                        }
                                    ]
                                }
                            ]
                        }
                    ]
                }
            ]
        }
    ]
}